[1,0,0,[["cc.JsonAsset",["_name","json"],1]],[[0,0,1,3]],[[0,"moon14",{"path":[{"centerPos":{"x":-470,"y":402},"startPos":{"x":-523,"y":463},"endPos":{"x":-416,"y":341},"blockSize":{"wid":107,"hei":122}},{"centerPos":{"x":-327,"y":350},"startPos":{"x":-381,"y":424},"endPos":{"x":-273,"y":276},"blockSize":{"wid":108,"hei":148}},{"centerPos":{"x":-245,"y":110},"startPos":{"x":-315,"y":171},"endPos":{"x":-174,"y":49},"blockSize":{"wid":141,"hei":122}},{"centerPos":{"x":-128,"y":210},"startPos":{"x":-160,"y":263},"endPos":{"x":-95,"y":156},"blockSize":{"wid":65,"hei":107}},{"centerPos":{"x":-8,"y":247},"startPos":{"x":-62,"y":324},"endPos":{"x":46,"y":170},"blockSize":{"wid":108,"hei":154}},{"centerPos":{"x":225,"y":114},"startPos":{"x":147,"y":163},"endPos":{"x":303,"y":64},"blockSize":{"wid":156,"hei":99}},{"centerPos":{"x":566,"y":244},"startPos":{"x":518,"y":347},"endPos":{"x":614,"y":141},"blockSize":{"wid":96,"hei":206}},{"centerPos":{"x":425,"y":-237},"startPos":{"x":377,"y":-179},"endPos":{"x":473,"y":-296},"blockSize":{"wid":96,"hei":117}},{"centerPos":{"x":546,"y":-387},"startPos":{"x":615,"y":-464},"endPos":{"x":477,"y":-310},"blockSize":{"wid":138,"hei":154}},{"centerPos":{"x":-413,"y":-257},"startPos":{"x":-467,"y":-189},"endPos":{"x":-359,"y":-325},"blockSize":{"wid":108,"hei":136}}]}]],0,0,[],[],[]]